metamodels/__init__.py
metamodels/core.py
metamodels-0.1.0.dist-info/METADATA
metamodels-0.1.0.dist-info/WHEEL
metamodels-0.1.0.dist-info/top_level.txt
metamodels-0.1.0.dist-info/RECORD
